Cargo.lock
Cargo.toml
MANIFEST.in
README.md
__init__.py
build.rs
requirements-build.txt
requirements.txt
setup.py
src/CardanoSigner.py
src/__init__.py
src/cxx.h
src/lib.rs
src/lib.rs.h
src/signer.cpp
src/signer.h
src/signer.i
src/signer_wrap.cxx
src/cardano_python_signing_module.egg-info/PKG-INFO
src/cardano_python_signing_module.egg-info/SOURCES.txt
src/cardano_python_signing_module.egg-info/dependency_links.txt
src/cardano_python_signing_module.egg-info/not-zip-safe
src/cardano_python_signing_module.egg-info/top_level.txt